biotmed_generic_entity_sdk/__init__.py
biotmed_generic_entity_sdk/api_client.py
biotmed_generic_entity_sdk/api_response.py
biotmed_generic_entity_sdk/configuration.py
biotmed_generic_entity_sdk/exceptions.py
biotmed_generic_entity_sdk/py.typed
biotmed_generic_entity_sdk/rest.py
biotmed_generic_entity_sdk/api/__init__.py
biotmed_generic_entity_sdk/api/generic_entity_api_api.py
biotmed_generic_entity_sdk/api/health_check_api_api.py
biotmed_generic_entity_sdk/models/__init__.py
biotmed_generic_entity_sdk/models/basic_entity_data.py
biotmed_generic_entity_sdk/models/basic_referenced_entity_data_uuidid.py
biotmed_generic_entity_sdk/models/basic_template_data.py
biotmed_generic_entity_sdk/models/create_generic_entity_by_template_name_request.py
biotmed_generic_entity_sdk/models/create_generic_entity_request.py
biotmed_generic_entity_sdk/models/error_response.py
biotmed_generic_entity_sdk/models/filter_v2.py
biotmed_generic_entity_sdk/models/generic_entity_response.py
biotmed_generic_entity_sdk/models/metadata.py
biotmed_generic_entity_sdk/models/order.py
biotmed_generic_entity_sdk/models/page_metadata.py
biotmed_generic_entity_sdk/models/parent_template_response.py
biotmed_generic_entity_sdk/models/reference_attribute_uuidid_request.py
biotmed_generic_entity_sdk/models/referenced_side_attribute_information.py
biotmed_generic_entity_sdk/models/search_request_v2.py
biotmed_generic_entity_sdk/models/search_response_generic_entity_response.py
biotmed_generic_entity_sdk/models/update_generic_entity_request.py
biotmed_generic_entity_sdk/models/version_response.py
biotmed_generic_entity_sdk-2.3.40.dist-info/METADATA
biotmed_generic_entity_sdk-2.3.40.dist-info/WHEEL
biotmed_generic_entity_sdk-2.3.40.dist-info/top_level.txt
biotmed_generic_entity_sdk-2.3.40.dist-info/RECORD
